indico_fonts/LiberationMono-Bold.ttf
indico_fonts/LiberationMono-BoldItalic.ttf
indico_fonts/LiberationMono-Italic.ttf
indico_fonts/LiberationMono-Regular.ttf
indico_fonts/LiberationSans-Bold.ttf
indico_fonts/LiberationSans-BoldItalic.ttf
indico_fonts/LiberationSans-Italic.ttf
indico_fonts/LiberationSans-Regular.ttf
indico_fonts/LiberationSerif-Bold.ttf
indico_fonts/LiberationSerif-BoldItalic.ttf
indico_fonts/LiberationSerif-Italic.ttf
indico_fonts/LiberationSerif-Regular.ttf
indico_fonts/LinBiolinum_R.otf
indico_fonts/LinBiolinum_RB.otf
indico_fonts/LinBiolinum_RI.otf
indico_fonts/LinLibertine_R.otf
indico_fonts/LinLibertine_RB.otf
indico_fonts/LinLibertine_RBI.otf
indico_fonts/LinLibertine_RBIah.ttf
indico_fonts/LinLibertine_RBah.ttf
indico_fonts/LinLibertine_RI.otf
indico_fonts/LinLibertine_RIah.ttf
indico_fonts/LinLibertine_Rah.ttf
indico_fonts/__init__.py
indico_fonts/kochi-gothic-subst.ttf
indico_fonts/kochi-mincho-subst.ttf
indico_fonts/uming.ttc
indico_fonts-1.1.dist-info/DESCRIPTION.rst
indico_fonts-1.1.dist-info/METADATA
indico_fonts-1.1.dist-info/RECORD
indico_fonts-1.1.dist-info/WHEEL
indico_fonts-1.1.dist-info/metadata.json
indico_fonts-1.1.dist-info/top_level.txt
