Metadata-Version: 1.1
Name: indico-fonts
Version: 1.1
Summary: Indico - Binary fonts
Home-page: http://indico.github.io
Author: Indico Team
Author-email: indico-team@cern.ch
License: Several
Platform: any
Classifier: License :: Other/Proprietary License
Classifier: Topic :: Text Processing :: Fonts
